eventstreams_sdk/__init__.py
eventstreams_sdk/adminrest_v1.py
eventstreams_sdk/common.py
eventstreams_sdk/version.py
eventstreams_sdk-1.1.1.dist-info/LICENSE
eventstreams_sdk-1.1.1.dist-info/METADATA
eventstreams_sdk-1.1.1.dist-info/WHEEL
eventstreams_sdk-1.1.1.dist-info/top_level.txt
eventstreams_sdk-1.1.1.dist-info/zip-safe
eventstreams_sdk-1.1.1.dist-info/RECORD
